iotawattpy/__init__.py
iotawattpy/connection.py
iotawattpy/const.py
iotawattpy/iotawatt.py
iotawattpy/sensor.py
iotawattpy-0.1.0.dist-info/LICENSE
iotawattpy-0.1.0.dist-info/METADATA
iotawattpy-0.1.0.dist-info/WHEEL
iotawattpy-0.1.0.dist-info/top_level.txt
iotawattpy-0.1.0.dist-info/RECORD
